README.rst
setup.py
bin/pygster
pygster/__init__.py
pygster/pygster_helper.py
pygster.egg-info/PKG-INFO
pygster.egg-info/SOURCES.txt
pygster.egg-info/dependency_links.txt
pygster.egg-info/not-zip-safe
pygster.egg-info/requires.txt
pygster.egg-info/top_level.txt
pygster/parsers/ECGateway.py
pygster/parsers/ErrorLogPygster.py
pygster/parsers/KVPygster.py
pygster/parsers/Log4jPygster.py
pygster/parsers/MetricPygster.py
pygster/parsers/PostfixPygster.py
pygster/parsers/SamplePygster.py
pygster/parsers/SquidPygster.py
pygster/parsers/__init__.py
pygster/parsers/stats_helper.py