Metadata-Version: 1.0
Name: pygster
Version: 1.0.0
Summary: Pygster
Home-page: https://github.com/OnBeep/pygster
Author: Greg Albrecht
Author-email: gba@onbeep.com
License:                     GNU GENERAL PUBLIC LICENSE
